caribou/__init__.py
caribou/config.py
caribou/agents/AgentSystem.py
caribou/agents/__init__.py
caribou/agents/create_agent_system.py
caribou/agents/integration_system.json
caribou/agents/olaf.json
caribou/agents/system_blueprint.json
caribou/auto_metrics/AutoMetric.py
caribou/auto_metrics/CellCountMetric.py
caribou/auto_metrics/CellTypingMetric.py
caribou/auto_metrics/IntegrationMetrics.py
caribou/cli/__init__.py
caribou/cli/config_cli.py
caribou/cli/create_agent_cli.py
caribou/cli/datasets_cli.py
caribou/cli/main.py
caribou/cli/run_cli.py
caribou/cli/utils_cli.py
caribou/code_samples/Celltyping.py
caribou/code_samples/DataCheck.py
caribou/code_samples/Doublets.py
caribou/code_samples/Downstream.py
caribou/code_samples/Downstream_gpu.py
caribou/code_samples/Integrate_Harmony.py
caribou/code_samples/Integrate_scvi.py
caribou/code_samples/MAD.py
caribou/code_samples/QC_Inspection.py
caribou/code_samples/QC_umap_visualization.py
caribou/code_samples/Re-analysis_afterQC.py
caribou/code_samples/Re-analysis_afterQC_gpu.py
caribou/code_samples/gene_check.py
caribou/code_samples/load_adata.py
caribou/code_samples/ref_train_celltypist.py
caribou/core/__init__.py
caribou/core/io_helpers.py
caribou/core/ollama_wrapper.py
caribou/core/sandbox_management.py
caribou/datasets/czi_datasets.py
caribou/datasets/spatial_transcriptomics_in_mouse_puck_191109_14.h5ad
caribou/datasets/spatial_transcriptomics_in_mouse_puck_191109_14.json
caribou/datasets/thymus_scrna-seq_atlas_-_myeloid_p2_subset.h5ad
caribou/datasets/thymus_scrna-seq_atlas_-_myeloid_p2_subset.json
caribou/execution/__init__.py
caribou/execution/runner.py
caribou/rag/RetrievalAugmentedGeneration.py
caribou/rag/__init__.py
caribou/rag/embeddings.jsonl
caribou/rag/functions.jsonl
caribou/sandbox/Dockerfile
caribou/sandbox/Singularity
caribou/sandbox/__init__.py
caribou/sandbox/benchmarking_sandbox_management.py
caribou/sandbox/benchmarking_sandbox_management_singularity.py
caribou/sandbox/kernel_api.py
caribou_cli-0.1.2.dist-info/METADATA
caribou_cli-0.1.2.dist-info/WHEEL
caribou_cli-0.1.2.dist-info/entry_points.txt
caribou_cli-0.1.2.dist-info/licenses/LICENSE
caribou_cli-0.1.2.dist-info/RECORD
