Metadata-Version: 2.4
Name: caribou-cli
Version: 0.1.2
Summary: Computational AI Research Interface for Bioinformatics, Omics, and Unifying Agents
Author: Dylan Riffle, Nima Shirooni
License-File: LICENSE
Requires-Python: >=3.10
Requires-Dist: cellxgene-census
Requires-Dist: docker
Requires-Dist: jupyter-client
Requires-Dist: nbformat
Requires-Dist: numpy
Requires-Dist: openai
Requires-Dist: platformdirs
Requires-Dist: python-dotenv
Requires-Dist: rich
Requires-Dist: sentence-transformers
Requires-Dist: tf-keras
Requires-Dist: tiledbsoma
Requires-Dist: typer
Provides-Extra: dev
Requires-Dist: ipykernel; extra == 'dev'
Requires-Dist: mypy; extra == 'dev'
Requires-Dist: pytest; extra == 'dev'
Requires-Dist: ruff; extra == 'dev'
